dmarc_report/__init__.py
dmarc_report/display.py
dmarc_report/parser.py
dmarc_report/report.py
dmarc_report/schema.py
dmarc_report-1.1.0.dist-info/METADATA
dmarc_report-1.1.0.dist-info/WHEEL
dmarc_report-1.1.0.dist-info/entry_points.txt
dmarc_report-1.1.0.dist-info/licenses/LICENSE
dmarc_report-1.1.0.dist-info/RECORD
