Metadata-Version: 2.3
Name: dmarc-report
Version: 1.1.0
Summary: Displays a nicely formatted report in your terminal from a DMARC XML report.
Project-URL: Homepage, https://github.com/stuartmaxwell/dmarc-report
Project-URL: Repository, https://github.com/stuartmaxwell/dmarc-report
Project-URL: Issues, https://github.com/stuartmaxwell/dmarc-report/issues
Author-email: Stuart Maxwell <stuart@amanzi.nz>
License: MIT License
Keywords: dkim,dmarc,dmarc-report,dmarc-xml,email,security,spf
Classifier: License :: OSI Approved :: MIT License
Classifier: Operating System :: OS Independent
Classifier: Programming Language :: Python
Classifier: Programming Language :: Python :: 3
Classifier: Programming Language :: Python :: 3 :: Only
Classifier: Programming Language :: Python :: 3.9
Classifier: Programming Language :: Python :: 3.10
Classifier: Programming Language :: Python :: 3.11
Classifier: Programming Language :: Python :: 3.12
Classifier: Programming Language :: Python :: 3.13
Requires-Python: >=3.9
Requires-Dist: defusedxml>=0.7.1
Requires-Dist: rich>=13.9.4
Provides-Extra: test
Requires-Dist: nox>=2024.10.9; extra == 'test'
Requires-Dist: pytest>=8.3.4; extra == 'test'
